{
  "app_updated_feed": "Quandu un postu h\u00e8 aghjuntu \u00e0 Feed",
  "app_confirmation_events": "Event rsvp h\u00e8 dumandatu da m\u00e8",
  "app_submission_events": "U mo rsvp di l&#39;avvenimentu h\u00e8 rispostu",
  "app_requested_forms": "A presentazione di u modulu h\u00e8 dumandatu da m\u00e8",
  "app_submission_forms": "U mo furmulariu h\u00e8 sottumessu da qualchissia",
  "app_requested_signs": "A presentazione di a firma h\u00e8 dumandata da m\u00e8",
  "app_submission_signs": "U mo documentu h\u00e8 firmatu da qualchissia",
  "app_requested_tasks": "U compitu h\u00e8 dumandatu da m\u00e8",
  "app_submission_tasks": "U mo compitu h\u00e8 cumpletu da qualchissia",
  "app_requested_invoices": "A presentazione di a fattura h\u00e8 dumandata da m\u00e8",
  "app_submission_invoices": "A mo fattura h\u00e8 pagata da qualchissia"
}
